xstrings/__init__.py
x_strings-0.1.2.dist-info/METADATA
x_strings-0.1.2.dist-info/WHEEL
x_strings-0.1.2.dist-info/RECORD
