Metadata-Version: 2.1
Name: x-strings
Version: 0.1.2
Summary: Extend Python syntax by defining custom string prefix
Home-page: https://github.com/gergelyk/xstrings/
License: MIT
Author: Grzegorz Krason
Author-email: grzegorz.krason@gmail.com
Requires-Python: >=3.9,<4.0
Classifier: License :: OSI Approved :: MIT License
Classifier: Programming Language :: Python :: 3
Classifier: Programming Language :: Python :: 3.9
Classifier: Programming Language :: Python :: 3.10
Classifier: Programming Language :: Python :: 3.11
